{
    "pools": [
        {
            "rolls": 1,
            "entries": [
                {
                    "type": "minecraft:item",
                    "name": "bellsandwhistles:andesite_bogie_steps",
                    "functions": [
                        {
                            "function": "minecraft:set_count",
                            "count": {
                                "min": 1,
                                "max": 8
                            }
                        }
                    ]
                },
                {
                    "type": "minecraft:item",
                    "name": "bellsandwhistles:andesite_door_step",
                    "functions": [
                        {
                            "function": "minecraft:set_count",
                            "count": {
                                "min": 1,
                                "max": 8
                            }
                        }
                    ]
                },
                {
                    "type": "minecraft:item",
                    "name": "bellsandwhistles:andesite_grab_rails",
                    "functions": [
                        {
                            "function": "minecraft:set_count",
                            "count": {
                                "min": 1,
                                "max": 8
                            }
                        }
                    ]
                },
                {
                    "type": "minecraft:item",
                    "name": "create:analog_lever",
                    "functions": [
                        {
                            "function": "minecraft:set_count",
                            "count": {
                                "min": 1,
                                "max": 4
                            }
                        }
                    ]
                },
                {
                    "type": "minecraft:item",
                    "name": "create:andesite_door",
                    "functions": [
                        {
                            "function": "minecraft:set_count",
                            "count": {
                                "min": 1,
                                "max": 2
                            }
                        }
                    ]
                },
                {
                    "type": "minecraft:item",
                    "name": "create:andesite_scaffolding",
                    "functions": [
                        {
                            "function": "minecraft:set_count",
                            "count": {
                                "min": 8,
                                "max": 32
                            }
                        }
                    ]
                },
                {
                    "type": "minecraft:item",
                    "name": "create:copycat_panel",
                    "functions": [
                        {
                            "function": "minecraft:set_count",
                            "count": {
                                "min": 8,
                                "max": 32
                            }
                        }
                    ]
                },
                {
                    "type": "minecraft:item",
                    "name": "create:copycat_step",
                    "functions": [
                        {
                            "function": "minecraft:set_count",
                            "count": {
                                "min": 8,
                                "max": 32
                            }
                        }
                    ]
                },
                {
                    "type": "minecraft:item",
                    "name": "create:experience_block",
                    "functions": [
                        {
                            "function": "minecraft:set_count",
                            "count": {
                                "min": 1,
                                "max": 32
                            }
                        }
                    ]
                },
                {
                    "type": "minecraft:item",
                    "name": "create:experience_nugget",
                    "functions": [
                        {
                            "function": "minecraft:set_count",
                            "count": {
                                "min": 8,
                                "max": 32
                            }
                        }
                    ]
                },
                {
                    "type": "minecraft:item",
                    "name": "create:framed_glass",
                    "functions": [
                        {
                            "function": "minecraft:set_count",
                            "count": {
                                "min": 8,
                                "max": 32
                            }
                        }
                    ]
                },
                {
                    "type": "minecraft:item",
                    "name": "create:gantry_shaft",
                    "functions": [
                        {
                            "function": "minecraft:set_count",
                            "count": {
                                "min": 2,
                                "max": 16
                            }
                        }
                    ]
                },
                {
                    "type": "minecraft:item",
                    "name": "create:industrial_iron_block",
                    "functions": [
                        {
                            "function": "minecraft:set_count",
                            "count": {
                                "min": 2,
                                "max": 8
                            }
                        }
                    ]
                },
                {
                    "type": "minecraft:item",
                    "name": "create:metal_bracket",
                    "functions": [
                        {
                            "function": "minecraft:set_count",
                            "count": {
                                "min": 8,
                                "max": 32
                            }
                        }
                    ]
                },
                {
                    "type": "minecraft:item",
                    "name": "create:metal_girder",
                    "functions": [
                        {
                            "function": "minecraft:set_count",
                            "count": {
                                "min": 8,
                                "max": 32
                            }
                        }
                    ]
                },
                {
                    "type": "minecraft:item",
                    "name": "create:piston_extension_pole",
                    "functions": [
                        {
                            "function": "minecraft:set_count",
                            "count": {
                                "min": 8,
                                "max": 32
                            }
                        }
                    ]
                },
                {
                    "type": "minecraft:item",
                    "name": "create:turntable",
                    "functions": [
                        {
                            "function": "minecraft:set_count",
                            "count": {
                                "min": 1,
                                "max": 8
                            }
                        }
                    ]
                },
                {
                    "type": "minecraft:item",
                    "name": "create:wooden_bracket",
                    "functions": [
                        {
                            "function": "minecraft:set_count",
                            "count": {
                                "min": 2,
                                "max": 16
                            }
                        }
                    ]
                },
                {
                    "type": "minecraft:item",
                    "name": "createaddition:barbed_wire",
                    "functions": [
                        {
                            "function": "minecraft:set_count",
                            "count": {
                                "min": 1,
                                "max": 8
                            }
                        }
                    ]
                },
                {
                    "type": "minecraft:item",
                    "name": "createaddition:biomass",
                    "functions": [
                        {
                            "function": "minecraft:set_count",
                            "count": {
                                "min": 2,
                                "max": 16
                            }
                        }
                    ]
                },
                {
                    "type": "minecraft:item",
                    "name": "createaddition:copper_wire",
                    "functions": [
                        {
                            "function": "minecraft:set_count",
                            "count": {
                                "min": 1,
                                "max": 16
                            }
                        }
                    ]
                },
                {
                    "type": "minecraft:item",
                    "name": "createaddition:gold_wire",
                    "functions": [
                        {
                            "function": "minecraft:set_count",
                            "count": {
                                "min": 1,
                                "max": 16
                            }
                        }
                    ]
                },
                {
                    "type": "minecraft:item",
                    "name": "createaddition:iron_wire",
                    "functions": [
                        {
                            "function": "minecraft:set_count",
                            "count": {
                                "min": 1,
                                "max": 16
                            }
                        }
                    ]
                },
                {
                    "type": "minecraft:item",
                    "name": "createaddition:spool",
                    "functions": [
                        {
                            "function": "minecraft:set_count",
                            "count": {
                                "min": 1,
                                "max": 4
                            }
                        }
                    ]
                },
                {
                    "type": "minecraft:item",
                    "name": "createaddition:straw",
                    "functions": [
                        {
                            "function": "minecraft:set_count",
                            "count": {
                                "min": 1,
                                "max": 9
                            }
                        }
                    ]
                },
                {
                    "type": "minecraft:item",
                    "name": "createdeco:andesite_bars",
                    "functions": [
                        {
                            "function": "minecraft:set_count",
                            "count": {
                                "min": 2,
                                "max": 32
                            }
                        }
                    ]
                },
                {
                    "type": "minecraft:item",
                    "name": "createdeco:andesite_catwalk",
                    "functions": [
                        {
                            "function": "minecraft:set_count",
                            "count": {
                                "min": 8,
                                "max": 32
                            }
                        }
                    ]
                },
                {
                    "type": "minecraft:item",
                    "name": "createdeco:andesite_catwalk_railing",
                    "functions": [
                        {
                            "function": "minecraft:set_count",
                            "count": {
                                "min": 8,
                                "max": 32
                            }
                        }
                    ]
                },
                {
                    "type": "minecraft:item",
                    "name": "createdeco:andesite_catwalk_stairs",
                    "functions": [
                        {
                            "function": "minecraft:set_count",
                            "count": {
                                "min": 8,
                                "max": 32
                            }
                        }
                    ]
                },
                {
                    "type": "minecraft:item",
                    "name": "createdeco:andesite_sheet_metal",
                    "functions": [
                        {
                            "function": "minecraft:set_count",
                            "count": {
                                "min": 2,
                                "max": 16
                            }
                        }
                    ]
                },
                {
                    "type": "minecraft:item",
                    "name": "createdeco:gray_placard",
                    "functions": [
                        {
                            "function": "minecraft:set_count",
                            "count": {
                                "min": 2,
                                "max": 8
                            }
                        }
                    ]
                }
            ]
        }
    ]
}
